{
  "parent": "minecraft:recipes/root",
  "criteria": {
    "has_sensor": {
      "conditions": {
        "items": [
          {
            "items": [
              "plethora:module_sensor"
            ]
          }
        ]
      },
      "trigger": "minecraft:inventory_changed"
    },
    "has_the_recipe": {
      "conditions": {
        "recipe": "plethora:sensor_module_upgrade"
      },
      "trigger": "minecraft:recipe_unlocked"
    }
  },
  "requirements": [
    [
      "has_sensor",
      "has_the_recipe"
    ]
  ],
  "rewards": {
    "recipes": [
      "plethora:sensor_module_upgrade"
    ]
  },
  "sends_telemetry_event": true
}